Metadata-Version: 2.1
Name: cpunks-10k
Version: 0.1.0
Summary: CPUNKS-10K are subsets of the 10,000 labeled images in the CryptoPunks collection, organized & modified for use in Machine Learning research
Home-page: http://github.com/tnn1t1s/cpunks-10k
Author: Tnn1t1s
Author-email: tnn1t1s@protonmail.com
License: BSD
Platform: UNKNOWN
Classifier: Environment :: Console
Classifier: Intended Audience :: Developers
Classifier: License :: OSI Approved :: BSD License
Classifier: Operating System :: OS Independent
Classifier: Programming Language :: Python
Classifier: Programming Language :: Python :: 3
Classifier: Programming Language :: Python :: 3.6
Classifier: Programming Language :: Python :: 3.7
Classifier: Programming Language :: Python :: 3.8
Classifier: Programming Language :: Python :: 3.9
Classifier: Programming Language :: Python :: 3.10
Classifier: Programming Language :: Python :: 3 :: Only
Provides-Extra: dev
License-File: LICENSE.txt
